augmentify/__init__.py
augmentify/augmentations.py
augmentify/constants.py
augmentify/utils.py
augmentify/variables.py
augmentify/wrapper.py
augmentify-0.1.dist-info/METADATA
augmentify-0.1.dist-info/WHEEL
augmentify-0.1.dist-info/top_level.txt
augmentify-0.1.dist-info/RECORD
