Metadata-Version: 2.1
Name: augmentify
Version: 0.1
Summary: none
Home-page: https://github.com/Karol-G/augmentify
Author-email: karol.gotkowski@dkfz.de
License: private
Requires-Dist: numpy
Requires-Dist: scikit-image
Requires-Dist: scipy
